Demo.py
Demo/Demo.png
graphclass/__init__.py
graphclass/_version.py
graphclass/graphclass.py
graphclass/template/html.j2
graphclass-0.0.32.dist-info/LICENSE
graphclass-0.0.32.dist-info/METADATA
graphclass-0.0.32.dist-info/WHEEL
graphclass-0.0.32.dist-info/top_level.txt
graphclass-0.0.32.dist-info/RECORD
