Metadata-Version: 2.1
Name: graphclass
Version: 0.0.32
Summary: Drawing graphs by graphviz with class approach
Author-email: nummulith <nummulith@gmail.com>
License: MIT
Project-URL: Homepage, https://github.com/nummulith/graphclass
Keywords: drawing,graph,graphviz
Classifier: Programming Language :: Python :: 3
Classifier: License :: OSI Approved :: MIT License
Classifier: Operating System :: OS Independent
Requires-Python: >=3.8
License-File: LICENSE
